AUTHORS
LICENSE
MANIFEST.in
README.rst
setup.py
django_nadb.egg-info/PKG-INFO
django_nadb.egg-info/SOURCES.txt
django_nadb.egg-info/dependency_links.txt
django_nadb.egg-info/requires.txt
django_nadb.egg-info/top_level.txt
docs/Makefile
docs/conf.py
docs/index.rst
docs/_build/doctrees/environment.pickle
docs/_build/doctrees/index.doctree
docs/_build/html/.buildinfo
docs/_build/html/genindex.html
docs/_build/html/index.html
docs/_build/html/objects.inv
docs/_build/html/search.html
docs/_build/html/searchindex.js
docs/_build/html/_sources/index.txt
docs/_build/html/_static/ajax-loader.gif
docs/_build/html/_static/basic.css
docs/_build/html/_static/comment-bright.png
docs/_build/html/_static/comment-close.png
docs/_build/html/_static/comment.png
docs/_build/html/_static/default.css
docs/_build/html/_static/doctools.js
docs/_build/html/_static/down-pressed.png
docs/_build/html/_static/down.png
docs/_build/html/_static/file.png
docs/_build/html/_static/jquery.js
docs/_build/html/_static/minus.png
docs/_build/html/_static/plus.png
docs/_build/html/_static/pygments.css
docs/_build/html/_static/searchtools.js
docs/_build/html/_static/sidebar.js
docs/_build/html/_static/underscore.js
docs/_build/html/_static/up-pressed.png
docs/_build/html/_static/up.png
docs/_build/html/_static/websupport.js
nadb/__init__.py
nadb/admin.py
nadb/managers.py
nadb/models.py
nadb/urls.py
nadb/views.py
nadb/templates/base_nadb.html
nadb/templates/category_detail.html
nadb/templates/category_list.html
nadb/templates/post_archive_day.html
nadb/templates/post_archive_month.html
nadb/templates/post_archive_year.html
nadb/templates/post_detail.html
nadb/templates/post_list.html