Metadata-Version: 1.0
Name: django-nadb
Version: 0.1a1
Summary: Not Another Django Blog app!
Home-page: https://github.com/earonne/django-nadb/
Author: Daniel Aronne
Author-email: earonne@quxisto.com
License: BSD
Platform: UNKNOWN
Classifier: Development Status :: 3 - Alpha
Classifier: Environment :: Web Environment
Classifier: Intended Audience :: Developers
Classifier: License :: OSI Approved :: BSD License
Classifier: Operating System :: OS Independent
Classifier: Programming Language :: Python
Classifier: Topic :: Utilities
